<annotation>
	<folder>freshoranges</folder>
	<filename>translation_Screen Shot 2018-06-13 at 12.04.12 AM.png</filename>
	<path>C:\Users\pswaroop\Documents\images\freshoranges\translation_Screen Shot 2018-06-13 at 12.04.12 AM.png</path>
	<source>
		<database>Unknown</database>
	</source>
	<size>
		<width>456</width>
		<height>360</height>
		<depth>3</depth>
	</size>
	<segmented>0</segmented>
	<object>
		<name>fresh_oranges</name>
		<pose>Unspecified</pose>
		<truncated>1</truncated>
		<difficult>0</difficult>
		<bndbox>
			<xmin>100</xmin>
			<ymin>72</ymin>
			<xmax>456</xmax>
			<ymax>360</ymax>
		</bndbox>
	</object>
</annotation>
